kernelci/__init__.py
kernelci/build.py
kernelci/cli.py
kernelci/data.py
kernelci/elf.py
kernelci/rootfs.py
kernelci/storage.py
kernelci/test.py
kernelci/config/__init__.py
kernelci/config/build.py
kernelci/config/data.py
kernelci/config/lab.py
kernelci/config/rootfs.py
kernelci/config/test.py
kernelci/lab/__init__.py
kernelci/lab/lava.py
kernelci-1.0.data/scripts/kci_build
kernelci-1.0.data/scripts/kci_rootfs
kernelci-1.0.data/scripts/kci_test
kernelci-1.0.dist-info/COPYING
kernelci-1.0.dist-info/METADATA
kernelci-1.0.dist-info/WHEEL
kernelci-1.0.dist-info/top_level.txt
kernelci-1.0.dist-info/RECORD
