Metadata-Version: 2.1
Name: kernelci
Version: 1.0
Summary: KernelCI core functions
Home-page: https://github.com/kernelci/kernelci-core
Author: kernelci.org
Author-email: kernelci@groups.io
License: UNKNOWN
Platform: UNKNOWN
Classifier: Development Status :: 5 - Production/Stable
Classifier: Environment :: Console
Classifier: Intended Audience :: Developers
Classifier: License :: OSI Approved :: GNU Lesser General Public License v2 or later (LGPLv2+)
Classifier: Operating System :: OS Independent
Classifier: Operating System :: POSIX :: Linux
Classifier: Programming Language :: C
Classifier: Programming Language :: Python
Classifier: Programming Language :: Python :: 3.6
Classifier: Topic :: Software Development :: Build Tools
Classifier: Topic :: Software Development :: Testing
Requires-Python: >=3.6
Requires-Dist: jinja2
Requires-Dist: pyyaml
